klega/__init__.py
klega/data_processor.py
klega/data_reader.py
klega/korean_tokenizer.py
klega/ld_analyser.py
klega/main.py
klega/util.py
klega/web.py
klega-1.0.6.dist-info/LICENSE.txt
klega-1.0.6.dist-info/METADATA
klega-1.0.6.dist-info/WHEEL
klega-1.0.6.dist-info/top_level.txt
klega-1.0.6.dist-info/RECORD
